setup.py
contour/__init__.py
contour/contour.py
contour.egg-info/PKG-INFO
contour.egg-info/SOURCES.txt
contour.egg-info/dependency_links.txt
contour.egg-info/not-zip-safe
contour.egg-info/top_level.txt