Metadata-Version: 1.0
Name: contour
Version: 0.2.1
Summary: Python configuration.
Home-page: http://github.com/lyddonb/contour
Author: Beau Lyddon
Author-email: lyddonb@gamil.com
License: 
